anlis/__init__.py
anlis/convergence.py
anlis/criticalPoints.py
anlis/derivative.py
anlis/differential.py
anlis/integral.py
anlis/polynomial.py
anlis/py.typed
anlis/vector.py
anlis/multidimensional/__init__.py
anlis/multidimensional/contour.py
anlis/multidimensional/criticalPoints.py
anlis/multidimensional/derivative.py
anlis/multidimensional/differential.py
anlis/series/__init__.py
anlis/series/arithmetic.py
anlis/series/geometric.py
anlis/series/power.py
anlis/series/series.py
anlis/series/taylor.py
anlis-0.1.3.dist-info/METADATA
anlis-0.1.3.dist-info/WHEEL
anlis-0.1.3.dist-info/licenses/LICENSE
anlis-0.1.3.dist-info/RECORD
