Metadata-Version: 2.1
Name: anlis
Version: 0.1.3
Summary: analysis library for python
Project-URL: Homepage, https://github.com/dxstiny/anlis
Project-URL: Bug Tracker, https://github.com/dxstiny/anlis/issues
Author-email: dxstiny <dxstiny.gh@gmail.com>
License: Mozilla Public License Version 2.0
License-File: LICENSE
Classifier: License :: OSI Approved :: MIT License
Classifier: Operating System :: OS Independent
Classifier: Programming Language :: Python :: 3
Requires-Python: >=3.9
